Metadata-Version: 2.1
Name: linkedin-dl
Version: 0.0.8
Summary: LinkedIn video downloader.
Home-page: https://github.com/jmgomezsoriano/linkedin-dl
Author: José Manuel Gómez Soriano
Author-email: jmgomez.soriano@gmail.com
License: LGPL2
Platform: UNKNOWN
Classifier: Programming Language :: Python :: 3
Classifier: License :: OSI Approved :: MIT License
Classifier: Operating System :: OS Independent
Requires-Python: >=3.7
